dgpylibs/__init__.py
dgpylibs/__main__.py
dgpylibs/_meta.py
dgpylibs/dev/__init__.py
dgpylibs/py.typed
dgpylibs-0.0.5.dist-info/METADATA
dgpylibs-0.0.5.dist-info/WHEEL
dgpylibs-0.0.5.dist-info/RECORD
