Metadata-Version: 2.1
Name: dgpylibs
Version: 0.0.5
Summary: Dynamic Graphics Python libraries
Home-page: https://github.com/dynamic-graphics-inc/dgpy-libs
License: MIT
Keywords: dgpy,dgi,typed,python3
Author: jessekrubin
Author-email: jesse@dgi.com
Requires-Python: >=3.8,<4.0
Classifier: Development Status :: 5 - Production/Stable
Classifier: Intended Audience :: Developers
Classifier: License :: OSI Approved :: MIT License
Classifier: Programming Language :: Python
Classifier: Programming Language :: Python :: 3
Classifier: Programming Language :: Python :: 3.8
Classifier: Programming Language :: Python :: 3.9
Classifier: Programming Language :: Python :: 3.10
Classifier: Programming Language :: Python :: 3.11
Classifier: Programming Language :: Python :: 3
Classifier: Programming Language :: Python :: 3.10
Classifier: Programming Language :: Python :: 3.8
Classifier: Programming Language :: Python :: 3.9
Classifier: Typing :: Typed
Requires-Dist: aiopen
Requires-Dist: asyncify
Requires-Dist: fmts
Requires-Dist: funkify
Requires-Dist: h5 (>=0.8.8)
Requires-Dist: jsonbourne
Requires-Dist: lager (>=0.17.0)
Requires-Dist: listless
Requires-Dist: requires
Requires-Dist: shellfish
Requires-Dist: xtyping
Project-URL: Repository, https://github.com/dynamic-graphics-inc/dgpy-libs
